{
    "logo": {
        "altText": "Logo light",
        "type": "ImageBlock"
    },
    "text": "🪐 Web Land Desarrollo web\n",
    "socialLinks": [
        {
            "altText": "GitHub link",
            "url": "https://github.com/augustosz",
            "icon": "github",
            "type": "Social"
        },
        {
            "altText": "LinkedIn link",
            "url": "",
            "icon": "linkedin",
            "type": "Social"
        },
        {
            "altText": "Email link",
            "url": "/dossantosaugusto36@gmail.com",
            "icon": "mail",
            "type": "Social"
        }
    ],
    "legalLinks": [],
    "copyrightText": "Powered by [Netlify](https://www.netlify.com/)\n",
    "colors": "bg-dark-fg-light",
    "type": "Footer",
    "styles": {
        "self": {
            "padding": [
                "pt-2"
            ],
            "margin": [
                "mt-0"
            ]
        }
    }
}